.mailmap
.testr.conf
AUTHORS
CONTRIBUTING.rst
ChangeLog
LICENSE
MANIFEST.in
README.rst
requirements.txt
setup.cfg
setup.py
test-requirements.txt
tox.ini
doc/source/conf.py
doc/source/index.rst
doc/source/packagers.rst
doc/source/semver.rst
doc/source/_templates/.placeholder
doc/source/_theme/layout.html
doc/source/_theme/theme.conf
doc/source/static/basic.css
doc/source/static/default.css
doc/source/static/header-line.gif
doc/source/static/header_bg.jpg
doc/source/static/jquery.tweet.js
doc/source/static/nature.css
doc/source/static/openstack_logo.png
doc/source/static/tweaks.css
pbr/__init__.py
pbr/core.py
pbr/extra_files.py
pbr/find_package.py
pbr/packaging.py
pbr/testr_command.py
pbr/util.py
pbr/version.py
pbr/hooks/__init__.py
pbr/hooks/backwards.py
pbr/hooks/base.py
pbr/hooks/commands.py
pbr/hooks/files.py
pbr/hooks/metadata.py
pbr/tests/__init__.py
pbr/tests/base.py
pbr/tests/test_commands.py
pbr/tests/test_core.py
pbr/tests/test_files.py
pbr/tests/test_hooks.py
pbr/tests/test_packaging.py
pbr/tests/test_setup.py
pbr/tests/test_version.py
pbr/tests/util.py
pbr/tests/testpackage/CHANGES.txt
pbr/tests/testpackage/LICENSE.txt
pbr/tests/testpackage/MANIFEST.in
pbr/tests/testpackage/README.txt
pbr/tests/testpackage/extra-file.txt
pbr/tests/testpackage/git-extra-file.txt
pbr/tests/testpackage/setup.cfg
pbr/tests/testpackage/setup.py
pbr/tests/testpackage/data_files/a.txt
pbr/tests/testpackage/data_files/b.txt
pbr/tests/testpackage/data_files/c.rst
pbr/tests/testpackage/pbr_testpackage/__init__.py
pbr/tests/testpackage/pbr_testpackage/_setup_hooks.py
pbr/tests/testpackage/pbr_testpackage/cmd.py
pbr/tests/testpackage/pbr_testpackage/package_data/1.txt
pbr/tests/testpackage/pbr_testpackage/package_data/2.txt
pbr/tests/testpackage/src/testext.c
pbr_samstav.egg-info/PKG-INFO
pbr_samstav.egg-info/SOURCES.txt
pbr_samstav.egg-info/dependency_links.txt
pbr_samstav.egg-info/entry_points.txt
pbr_samstav.egg-info/not-zip-safe
pbr_samstav.egg-info/requires.txt
pbr_samstav.egg-info/top_level.txt
tools/integration.sh